{"chunk_definitions":[{"row":13,"row_count":1,"visible":true,"expansion_state":0,"options":{"include":false,"engine":"r","label":"setup"},"document_id":"DA82AF1A","chunk_id":"csetup_chunk","chunk_label":"setup"},{"row":25,"row_count":1,"visible":true,"expansion_state":0,"options":{"engine":"r","label":"unnamed-chunk-1"},"document_id":"DA82AF1A","chunk_id":"cu6uv53u7im60","chunk_label":"unnamed-chunk-1"},{"row":31,"row_count":1,"visible":true,"expansion_state":0,"options":{"engine":"r","label":"unnamed-chunk-2"},"document_id":"DA82AF1A","chunk_id":"ctflm7knuqhmp","chunk_label":"unnamed-chunk-2"},{"row":38,"row_count":1,"visible":true,"expansion_state":0,"options":{"engine":"r","label":"unnamed-chunk-3"},"document_id":"DA82AF1A","chunk_id":"c3jnishdrva0v","chunk_label":"unnamed-chunk-3"},{"row":48,"row_count":1,"visible":true,"expansion_state":0,"options":{"engine":"r","label":"unnamed-chunk-4"},"document_id":"DA82AF1A","chunk_id":"cskv856dpazwp","chunk_label":"unnamed-chunk-4"},{"row":69,"row_count":1,"visible":true,"expansion_state":0,"options":{"engine":"r","label":"unnamed-chunk-5"},"document_id":"DA82AF1A","chunk_id":"cmt4f45yimf9e","chunk_label":"unnamed-chunk-5"},{"row":86,"row_count":1,"visible":true,"expansion_state":0,"options":{"engine":"r","label":"unnamed-chunk-6"},"document_id":"DA82AF1A","chunk_id":"cvzlm2eb8soa1","chunk_label":"unnamed-chunk-6"},{"row":104,"row_count":1,"visible":true,"expansion_state":0,"options":{"engine":"r","label":"unnamed-chunk-7"},"document_id":"DA82AF1A","chunk_id":"cx5r6etzcufb0","chunk_label":"unnamed-chunk-7"},{"row":119,"row_count":1,"visible":true,"expansion_state":0,"options":{"engine":"r","label":"unnamed-chunk-2"},"document_id":"DA82AF1A","chunk_id":"cusi3a6dx1oxh","chunk_label":"unnamed-chunk-8"},{"row":161,"row_count":1,"visible":true,"expansion_state":0,"options":{"engine":"r","label":"unnamed-chunk-8"},"document_id":"DA82AF1A","chunk_id":"ciuyv3z8hsu8e","chunk_label":"unnamed-chunk-9"},{"row":187,"row_count":1,"visible":true,"expansion_state":0,"options":{"engine":"r","label":"unnamed-chunk-9"},"document_id":"DA82AF1A","chunk_id":"ckgv8zhua05xw","chunk_label":"unnamed-chunk-10"}],"doc_write_time":1648136930,"working_dir":"/Users/niveditakanrar/Documents/Elowitz Lab/motifs","default_chunk_options":{}}